MANIFEST.in
setup.cfg
setup.py
django_piston_0_2_3_patch_init.egg-info/PKG-INFO
django_piston_0_2_3_patch_init.egg-info/SOURCES.txt
django_piston_0_2_3_patch_init.egg-info/dependency_links.txt
django_piston_0_2_3_patch_init.egg-info/top_level.txt
piston/__init__.py