Metadata-Version: 1.0
Name: django-piston-0-2-3-patch-init
Version: 0.2.3
Summary: Piston omits __init__.py in its pkg, so pip installs dont work unless you add a patch like this.
Home-page: UNKNOWN
Author: Vijay Ragavan
Author-email: vijay@moneychakra.com
License: BSD
Platform: UNKNOWN
Classifier: Development Status :: 3 - Alpha
Classifier: Framework :: Django
Classifier: Intended Audience :: Developers
Classifier: License :: OSI Approved :: BSD License
Classifier: Operating System :: OS Independent
Classifier: Programming Language :: Python
Classifier: Topic :: Internet :: WWW/HTTP
